{"components/common/currency-selector":"{{#if currency_selector.currencies.length '>' 1}}\n<ul class=\"navUser-section\">\n    <li class=\"navUser-item\">\n        <a class=\"navUser-action navUser-action--currencySelector has-dropdown\" href=\"#\" data-dropdown=\"currencySelection\" aria-controls=\"currencySelection\" aria-expanded=\"false\">{{{currency_selector.active_currency_flag}}} {{currency_selector.active_currency_code}} <i class=\"icon\" aria-hidden=\"true\"><svg><use xlink:href=\"#icon-chevron-down\" /></svg></i></a>\n        <ul class=\"dropdown-menu\" id=\"currencySelection\" data-dropdown-content aria-hidden=\"true\" tabindex=\"-1\">\n            {{#each currency_selector.currencies}}\n            <li class=\"dropdown-menu-item\">\n                <a href=\"{{{switch_url}}}\"\n                   data-currency-code=\"{{{code}}}\"\n                   {{#if cart_currency_switch_url.length '>' 0 }}\n                   data-cart-currency-switch-url=\"{{{cart_currency_switch_url}}}\"\n                   {{/if}}\n                   data-warning=\"{{lang 'common.currency_switch_promotion'}}\"\n                >\n                    {{#if is_active}}\n                    <strong>{{{flag}}} {{name}}</strong>\n                    {{else}}\n                    {{{flag}}} {{name}}\n                    {{/if}}\n                </a>\n            </li>\n            {{/each}}\n        </ul>\n    </li>\n</ul>\n{{/if}}\n","components/common/header":"<a href=\"#main-content\" class=\"skip-to-main-link\">{{lang 'header.skip_to_main'}}</a>\n{{#if theme_settings.use-yotpo}}\n    <input type=\"hidden\" value=\"{{theme_settings.yotpo-app-key}}\" name=\"yotpo_key\" id=\"yotpo-key\">\n{{/if}}\n<header class=\"site-header\">\n    <section class=\"top-bar\">\n        {{> components/epicHeader/top-bar}}\n    </section>\n    <section class=\"logo-bar\">\n        {{> components/epicHeader/logo-bar}}\n    </section>\n    <section class=\"mob-header\">\n        {{> components/epicHeader/mob-header}}\n    </section>\n    <div class=\"cs-navbar nav-bar main-nav-bar mob-hide{{#if theme_settings.left-category-menu}} sc-menu{{/if}}\">\n        {{#if theme_settings.left-category-menu}}\n            {{> components/epicNavbar/sidebar-category-menu}}\n        {{else}}\n            {{> components/epicNavbar/default-nav-menu}}\n        {{/if}}\n    </div>\n</header>\n{{#if banners.top}}\n<div class=\"banners\" data-banner-location=\"top\">\n    {{#each (limit banners.top_metadata 1)}}\n    <div class=\"banner\" data-event-type=\"promotion\" data-entity-id=\"{{this.id}}\" data-name=\"{{this.banner-name}}\" data-position=\"{{this.location}}\" data-banner-id=\"{{this.banner-name}}\">\n        <div data-event-type=\"promotion-click\">\n            {{{this.content}}}\n        </div>\n    </div>\n    {{/each}}\n</div>\n{{/if}}\n{{{region name=\"header_bottom--global\"}}}\n{{{region name=\"header_bottom\"}}}\n","components/common/mobile-logo":"<a href=\"{{urls.home}}\">\r\n    <img    class=\"img-responsive\" \r\n            src=\"{{getImage theme_settings.mobile-logo}}\" \r\n            alt=\"{{settings.store_logo.title}}\" \r\n            title=\"{{settings.store_logo.title}}\" \r\n    />\r\n</a>\n","components/common/navigation-dropdown":"<div class=\"navPage-subMenu navPage-subMenu-horizontal\" id=\"navPages-{{id}}\" aria-hidden=\"true\" tabindex=\"-1\">\n    <ul class=\"navPage-subMenu-list\">\n        <!-- <li class=\"navPage-subMenu-item-parent\">\n            <a class=\"navPage-subMenu-action navPages-action navPages-action-depth-max\" href=\"{{url}}\">{{lang 'category.view_all.name' category=name}}</a>\n        </li> -->\n        {{#each children}}\n            <li class=\"navPage-subMenu-item-child\">\n                {{#if children}}\n                    <a class=\"navPage-subMenu-action navPages-action navPages-action-depth-max has-subMenu{{#if is_active}} activePage{{/if}}\" href=\"{{url}}\" data-collapsible=\"navPages-{{id}}\">\n                        {{name}} <i class=\"icon navPages-action-moreIcon\" aria-hidden=\"true\"><svg><use xlink:href=\"#icon-chevron-down\" /></svg></i>\n                    </a>\n                    {{> components/common/navigation-dropdown}}\n                {{else}}\n                    <a class=\"navPage-subMenu-action navPages-action{{#if is_active}} activePage{{/if}}\" href=\"{{url}}\">{{name}}</a>\n                {{/if}}\n            </li>\n        {{/each}}\n    </ul>\n</div>\n","components/common/navigation-list":"{{#if children}}\n<a class=\"navPages-action has-subMenu{{#if is_active}} activePage{{/if}}\"\n   href=\"{{url}}\"\n   data-collapsible=\"navPages-{{id}}\"\n>\n    {{name}}\n    <i class=\"icon navPages-action-moreIcon\" aria-hidden=\"true\">\n        <svg><use xlink:href=\"#icon-chevron-down\" /></svg>\n    </i>\n</a>\n<div class=\"navPage-subMenu\" id=\"navPages-{{id}}\" aria-hidden=\"true\" tabindex=\"-1\">\n    <ul class=\"navPage-subMenu-list\">\n        <li class=\"navPage-subMenu-item\">\n            <a class=\"navPage-subMenu-action navPages-action\"\n               href=\"{{url}}\"\n               aria-label=\"{{lang 'category.view_all.name' category=name}}\"\n            >\n                {{lang 'category.view_all.name' category=name}}\n            </a>\n        </li>\n        {{#each children}}\n            <li class=\"navPage-subMenu-item\">\n                {{#if children}}\n                    <a class=\"navPage-subMenu-action navPages-action has-subMenu{{#if is_active}} activePage{{/if}}\"\n                       href=\"{{url}}\"\n                       aria-label=\"{{name}}\"\n                    >\n                        {{name}}\n                        <span class=\"collapsible-icon-wrapper\"\n                            data-collapsible=\"navPages-{{id}}\"\n                            data-collapsible-disabled-breakpoint=\"medium\"\n                            data-collapsible-disabled-state=\"open\"\n                            data-collapsible-enabled-state=\"closed\"\n                        >\n                            <i class=\"icon navPages-action-moreIcon\" aria-hidden=\"true\">\n                                <svg><use xlink:href=\"#icon-chevron-down\" /></svg>\n                            </i>\n                        </span>\n                    </a>\n                    <ul class=\"navPage-childList\" id=\"navPages-{{id}}\">\n                        {{#each children}}\n                        <li class=\"navPage-childList-item\">\n                            <a class=\"navPage-childList-action navPages-action{{#if is_active}} activePage{{/if}}\"\n                               href=\"{{url}}\"\n                               aria-label=\"{{name}}\"\n                            >\n                                {{name}}\n                            </a>\n                        </li>\n                        {{/each}}\n                    </ul>\n                {{else}}\n                    <a class=\"navPage-subMenu-action navPages-action{{#if is_active}} activePage{{/if}}\"\n                       href=\"{{url}}\"\n                       aria-label=\"{{name}}\"\n                    >\n                        {{name}}\n                    </a>\n                {{/if}}\n            </li>\n        {{/each}}\n    </ul>\n</div>\n{{else}}\n<a class=\"navPages-action{{#if is_active}} activePage{{/if}}\"\n   href=\"{{url}}\"\n   aria-label=\"{{name}}\"\n>\n    {{name}}\n</a>\n{{/if}}\n","components/common/navigation-list-alternate":"{{#if children}}\n    <a class=\"navPages-action navPages-action-depth-max has-subMenu is-root{{#if is_active}} activePage{{/if}}\"\n       href=\"{{url}}\"\n       data-collapsible=\"navPages-{{id}}\"\n       aria-label=\"{{name}}\"\n    >\n        {{name}}\n        <i class=\"icon navPages-action-moreIcon\" aria-hidden=\"true\">\n            <svg><use xlink:href=\"#icon-chevron-down\" /></svg>\n        </i>\n    </a>\n    {{> components/common/navigation-dropdown}}\n{{else}}\n    <a class=\"navPages-action{{#if is_active}} activePage{{/if}}\"\n       href=\"{{url}}\"\n       aria-label=\"{{name}}\"\n    >\n        {{name}}\n    </a>\n{{/if}}\n","components/common/navigation-menu":"<nav class=\"navPages\">\n    <div class=\"navPages-quickSearch\">\n        {{> components/common/quick-search name='nav-menu-quick-search'}}\n        <div class=\"mobile-call-us\">\n            <a href=\"tel:{{settings.phone_number}}\">{{lang 'epicHeader.call_us'}}</a>\n        </div>\n        {{#if customer}}\n        <div class=\"mobile-my-account\">\n            <a href=\"{{urls.account.index}}\">{{lang 'epicHeader.my_account'}}</a>\n        </div>\n        <div class=\"mobile-my-account\">\n            <a href=\"{{urls.auth.logout}}\">{{lang 'common.logout'}}</a>\n        </div>\n        {{else}}\n            <div class=\"mobile-my-account\">\n                <a href=\"{{urls.auth.login}}\">{{lang 'common.login'}} / {{lang 'common.sign_up'}}</a>\n            </div>\n        {{/if}}\n    </div>\n    <ul class=\"navPages-list{{#if theme_settings.navigation_design '!==' 'simple'}} navPages-list-depth-max{{/if}}\">\n        {{#each categories}}\n            <li class=\"navPages-item\">\n            {{#if ../theme_settings.navigation_design '===' 'simple'}}\n                {{> components/common/navigation-list}}\n            {{/if}}\n            {{#if ../theme_settings.navigation_design '===' 'alternate'}}\n                {{> components/common/navigation-list-alternate}}\n            {{/if}}\n            </li>\n        {{/each}}\n        {{#unless theme_settings.hide_content_navigation}}\n            {{#each pages}}\n                 <li class=\"navPages-item navPages-item-page\">\n                     <a class=\"navPages-action{{#if name '==' ../page.title}} activePage{{/if}}\"\n                        href=\"{{url}}\"\n                        aria-label=\"{{name}}\"\n                     >\n                         {{name}}\n                     </a>\n                 </li>\n             {{/each}}\n        {{/unless}}\n    </ul>\n    <ul class=\"navPages-list navPages-list--user\">\n        {{#if currency_selector.currencies.length '>' 1}}\n            <li class=\"navPages-item\">\n                <a class=\"navPages-action has-subMenu\"\n                   href=\"#\"\n                   data-collapsible=\"navPages-currency\"\n                   aria-controls=\"navPages-currency\"\n                   aria-expanded=\"false\"\n                   aria-label=\"{{lang 'common.currency' code=currency_selector.active_currency_code}}\"\n                >\n                    {{lang 'common.currency' code=currency_selector.active_currency_code}}\n                    <i class=\"icon navPages-action-moreIcon\" aria-hidden=\"true\">\n                        <svg>\n                            <use xmlns:xlink=\"http://www.w3.org/1999/xlink\" xlink:href=\"#icon-chevron-down\"></use>\n                        </svg>\n                    </i>\n                </a>\n                <div class=\"navPage-subMenu\" id=\"navPages-currency\" aria-hidden=\"true\" tabindex=\"-1\">\n                    <ul class=\"navPage-subMenu-list\">\n                        {{#each currency_selector.currencies}}\n                        <li class=\"navPage-subMenu-item\">\n                            <a class=\"navPage-subMenu-action navPages-action\"\n                               href=\"{{{switch_url}}}\"\n                               aria-label=\"{{name}}\"\n                               data-currency-code=\"{{{code}}}\"\n                               {{#if cart_currency_switch_url.length '>' 0 }}\n                               data-cart-currency-switch-url=\"{{{cart_currency_switch_url}}}\"\n                               {{/if}}\n                               data-warning=\"{{lang 'common.currency_switch_promotion'}}\"\n                            >\n                                {{#if is_active}}\n                                    <strong>{{name}}</strong>\n                                {{else}}\n                                    {{name}}\n                                {{/if}}\n                            </a>\n                        </li>\n                        {{/each}}\n                    </ul>\n                </div>\n            </li>\n        {{/if}}\n        {{#if settings.gift_certificates_enabled}}\n            <li class=\"navPages-item\">\n                <a class=\"navPages-action\"\n                   href=\"{{urls.gift_certificate.purchase}}\"\n                   aria-label=\"{{lang 'common.gift_cert'}}\"\n                >\n                    {{lang 'common.gift_cert'}}\n                </a>\n            </li>\n        {{/if}}\n        {{#if customer.store_credit.value '>' 0}}\n            <li class=\"navPages-item\">\n                <a class=\"navPages-action navPages-action--storeCredit\">\n                    {{lang 'common.store_credit_overview' credit=customer.store_credit.formatted}}\n                </a>\n            </li>\n        {{/if}}\n        {{#if theme_settings.product_list_display_mode '==' 'list'}}\n            <li class=\"navPages-item\">\n                <a class=\"navPages-action navPages-action--compare\"\n                   href=\"{{urls.compare}}\"\n                   data-compare-nav\n                   aria-label=\"{{lang 'common.compare'}}\"\n                >\n                    {{lang 'common.compare'}}\n                    <span class=\"countPill countPill--positive countPill--alt\"></span>\n                </a>\n            </li>\n        {{/if}}\n    </ul>\n</nav>\n","components/common/quick-search":"<div class=\"container\">\n    <form class=\"form\" onsubmit=\"return false\" data-url=\"{{urls.search}}\" data-quick-search-form>\n        <fieldset class=\"form-fieldset\">\n            <div class=\"form-field\">\n                <label class=\"is-srOnly\" for=\"{{name}}\">{{lang \"search.quick_search.input_label\"}}</label>\n                <input class=\"form-input\"\n                       data-search-quick\n                       name=\"{{name}}\"\n                       id=\"{{name}}\"\n                       data-error-message=\"{{lang 'search.error.empty_field'}}\"\n                       placeholder=\"{{lang 'search.quick_search.input_placeholder'}}\"\n                       autocomplete=\"off\"\n                >\n            </div>\n        </fieldset>\n    </form>\n    <section class=\"quickSearchResults\" data-bind=\"html: results\"></section>\n    <p role=\"status\"\n       aria-live=\"polite\"\n       class=\"aria-description--hidden\"\n       data-search-aria-message-predefined-text=\"{{{lang 'search.results.quick_count_live'}}}\"\n    ></p>\n</div>\n","components/common/store-logo":"<a href=\"{{urls.home}}\" class=\"header-logo__link\">\n    {{#if settings.store_logo.image}}\n        {{#if theme_settings.logo_size '===' 'original'}}\n            <img class=\"header-logo-image-unknown-size\" src=\"{{getImage settings.store_logo.image 'logo_size'}}\" alt=\"{{settings.store_logo.title}}\" title=\"{{settings.store_logo.title}}\">\n        {{else}}\n            <div class=\"header-logo-image-container\">\n                <img class=\"header-logo-image\" src=\"{{getImage settings.store_logo.image 'logo_size'}}\" alt=\"{{settings.store_logo.title}}\" title=\"{{settings.store_logo.title}}\">\n            </div>\n        {{/if}}\n    {{else}}\n        <span class=\"header-logo-text\">{{settings.store_logo.title}}</span>\n    {{/if}}\n</a>\n","components/epicHeader/logo-bar":"<div class=\"container\">\n    {{#if theme_settings.logo-position '==' 'left'}}\n        <div class=\"row align-items-center\">\n            <div class=\"col-md-3 col-lg-3\">\n                {{#if page_type '===' 'default'}}\n                    <h1 class=\"site-logo header-logo--left\">\n                        {{> components/common/store-logo}}\n                    </h1>\n                {{else}}\n                    <div class=\"site-logo header-logo--left\">\n                        {{> components/common/store-logo}}\n                    </div>\n                {{/if}}\n            </div>\n            <div class=\"{{#if theme_settings.left-category-menu}}col-md-7{{else}}col-md-6{{/if}} ml-auto\">\n                {{> components/epicHeader/search}}\n            </div>\n            {{#if settings.show_wishlist}}\n            <div class=\"col-auto{{#if theme_settings.left-category-menu '!==' true}} p-0{{/if}}\">\n                <ul class=\"logobar-nav\">\n                    <li>\n                        <a href=\"{{urls.account.wishlists.all}}\">\n                            <i class=\"fal fa-heart-circle\"></i>\n                            {{lang 'account.nav.wishlists' num_wishlists=customer.num_wishlists}}\n                        </a>\n                    </li>\n                </ul>\n            </div>\n            {{/if}}\n            {{#if theme_settings.left-category-menu '!==' true}}\n                {{#or customer (if theme_settings.restrict_to_login '!==' true)}}\n                    <div class=\"col-auto\">\n                        <div class=\"cart-section\">\n                            <div class=\"cart-items\">\n                                <span class=\"cart-quantity cart-items-count\">{{cart.quantity}}</span>\n                                <span class=\"icon\">\n                                    <svg><use xlink:href=\"#icon-shopping-cart\" /></svg> \n                                </span>\n                            </div>\n                            <div class=\"cart-subtotal\">\n                                <a\n                                    class=\"view-cart\"\n                                    data-cart-preview\n                                    data-dropdown=\"cart-preview-dropdown\"\n                                    href=\"{{urls.cart}}\" aria-label=\"{{lang 'cart.nav_aria_label'}}\">\n                                   <span>My Cart</span><br><span class=\"ct-price\">{{cart.grand_total.formatted}}</span> <i class=\"icon\" aria-hidden=\"true\"><svg><use xlink:href=\"#icon-chevron-down\" /></svg></i>\n                                </a>\n                                <div class=\"dropdown-menu\" id=\"cart-preview-dropdown\" data-dropdown-content aria-hidden=\"true\"></div>\n                            </div>\n                        </div>\n                    </div>\n                    {{else}}\n                {{/or}}\n            {{/if}}\n        </div><!--row-->\n    {{/if}}\n    {{#if theme_settings.logo-position '==' 'center'}}\n    <div class=\"row align-items-center\"> \n            <div class=\"col-lg-4 offset-lg-4\">\n                {{#if page_type '===' 'default'}}\n                    <h1 class=\"site-logo text-center\">\n                        {{> components/common/store-logo}}\n                    </h1>\n                {{else}}\n                    <div class=\"site-logo text-center\">\n                        {{> components/common/store-logo}}\n                    </div>\n                {{/if}} \n            </div>\n            {{#if settings.show_wishlist}}\n            <div class=\"col-auto ml-auto{{#if theme_settings.left-category-menu '!==' true}} p-0{{/if}}\">\n                <ul class=\"logobar-nav\">\n                    <li>\n                        <a href=\"{{urls.account.wishlists.all}}\">\n                            <i class=\"fal fa-heart-circle\"></i>\n                            {{lang 'account.nav.wishlists' num_wishlists=customer.num_wishlists}}\n                        </a>\n                    </li>\n                </ul>\n            </div>\n            {{/if}}\n            {{#if theme_settings.left-category-menu '!==' true}}\n                {{#or customer (if theme_settings.restrict_to_login '!==' true)}}\n                    <div class=\"col-auto\">\n                        <div class=\"cart-section\">\n                            <div class=\"cart-items\">\n                                <span class=\"cart-quantity cart-items-count\">{{cart.quantity}}</span>\n                                <span class=\"icon\">\n                                    <svg><use xlink:href=\"#icon-shopping-cart\" /></svg> \n                                </span>\n                            </div>\n                            <div class=\"cart-subtotal\">\n                                <a\n                                    class=\"view-cart\"\n                                    data-cart-preview\n                                    data-dropdown=\"cart-preview-dropdown\"\n                                    href=\"{{urls.cart}}\" aria-label=\"{{lang 'cart.nav_aria_label'}}\">\n                                   <span>My Cart</span><br><span class=\"ct-price\">{{cart.grand_total.formatted}}</span> <i class=\"icon\" aria-hidden=\"true\"><svg><use xlink:href=\"#icon-chevron-down\" /></svg></i>\n                                </a>\n                                <div class=\"dropdown-menu\" id=\"cart-preview-dropdown\" data-dropdown-content aria-hidden=\"true\"></div>\n                            </div>\n                        </div>\n                    </div>\n                    {{else}}\n                {{/or}}\n            {{/if}}\n        </div><!--row-->\n    {{/if}}\n    {{#if theme_settings.logo-position '==' 'right'}}\n        <div class=\"row align-items-center\">\n            {{#if theme_settings.left-category-menu '!==' true}}\n                {{#or customer (if theme_settings.restrict_to_login '!==' true)}}\n                    <div class=\"col-auto\">\n                        <div class=\"cart-section\">\n                            <div class=\"cart-items\">\n                                <span class=\"cart-quantity cart-items-count\">{{cart.quantity}}</span>\n                                <span class=\"icon\">\n                                    <svg><use xlink:href=\"#icon-shopping-cart\" /></svg> \n                                </span>\n                            </div>\n                            <div class=\"cart-subtotal cart-subtotal-left\">\n                                <a\n                                    class=\"view-cart\"\n                                    data-cart-preview\n                                    data-dropdown=\"cart-preview-dropdown\"\n                                    href=\"{{urls.cart}}\" aria-label=\"{{lang 'cart.nav_aria_label'}}\">\n                                   <span>My Cart</span><br><span class=\"ct-price\">{{cart.grand_total.formatted}}</span> <i class=\"icon\" aria-hidden=\"true\"><svg><use xlink:href=\"#icon-chevron-down\" /></svg></i>\n                                </a>\n                                <div class=\"dropdown-menu cart-p-right\" id=\"cart-preview-dropdown\" data-dropdown-content aria-hidden=\"true\"></div>\n                            </div>\n                        </div>\n                    </div>\n                    {{else}}\n                {{/or}}\n            {{/if}}\n            {{#if settings.show_wishlist}}\n            <div class=\"col-auto{{#if theme_settings.left-category-menu '!==' true}} p-0{{/if}}\">\n                <ul class=\"logobar-nav\">\n                    <li>\n                        <a href=\"{{urls.account.wishlists.all}}\">\n                            <i class=\"fal fa-heart-circle\"></i>\n                            {{lang 'account.nav.wishlists' num_wishlists=customer.num_wishlists}}\n                        </a>\n                    </li>\n                </ul>\n            </div>\n            {{/if}}\n            <div class=\"{{#if theme_settings.left-category-menu}}col-md-6{{else}}col-md-5{{/if}} mr-auto\">\n                {{> components/epicHeader/search}}\n            </div>\n            <div class=\"col-md-3 col-lg-3\">\n                {{#if page_type '===' 'default'}}\n                    <h1 class=\"site-logo header-logo--right\">\n                        {{> components/common/store-logo}}\n                    </h1>\n                {{else}}\n                    <div class=\"site-logo header-logo--right\">\n                        {{> components/common/store-logo}}\n                    </div>\n                {{/if}}\n            </div>\n        </div><!--row-->\n    {{/if}}\n    {{#if theme_settings.logo-position '!==' 'center'}}\n        <section class=\"quickSearchResults quick-search\" data-bind=\"html: results\"></section>\n    {{/if}}\n</div><!--container-->\n","components/epicHeader/mob-header":"  <div class=\"row align-items-center p-relative z-99\">\n    <div class=\"col-3\">\n        <a href=\"#main-content\" class=\"mobileMenu-toggle\" data-mobile-menu-toggle=\"menu\">\n            <span class=\"icon\">\n                <svg><use xlink:href=\"#icon-menu-search\" /></svg>\n            </span>\n        </a>\n    </div>\n    <div class=\"col-6 p-0\">\n        {{#if theme_settings.use-mobile-logo}}\n            {{> components/common/mobile-logo}}\n        {{else}}\n            {{> components/common/store-logo}}\n        {{/if}}\n    </div>\n    <div class=\"col-3 text-right mobile-cart-btn\">\n        <a href=\"{{urls.cart}}\">\n            <span class=\"navUser-item-cartLabel\">\n                <span class=\"icon\">\n                    <svg><use xlink:href=\"#icon-shopping-cart\" /></svg>\n                </span>\n            </span><span class=\"countPill{{#if cart.items}} countPill--positive{{/if}} cart-quantity\">{{cart.quantity}}</span>\n        </a>\n                    <!-- <div class=\"dropdown-menu\" id=\"cart-preview-dropdown\" data-dropdown-content aria-hidden=\"true\"></div> -->\n        \n    </div>\n</div>\n<div class=\"cs-navbar nav-bar\">\n    <div class=\"navPages-container\" id=\"menu\" data-menu>\n        {{> components/common/navigation-menu}}\n    </div>\n</div>\n","components/epicHeader/search":"<div class=\"header-search\">\n    <div class=\"container\">\n    <form class=\"form\" action=\"{{urls.search}}\">\n        <div class=\"search-input-field\">\n            <input class=\"search_\" name=\"search_query_adv\" data-search-quick type=\"search\" autocomplete=\"off\" onfocus=\"this.placeholder=''\" onblur=\"this.placeholder='{{theme_settings.header-search-text}}'\" placeholder=\"{{theme_settings.header-search-text}}\">\n            <button  class=\"button button--primary\" name=\"go\" value=\"Search for Resin, Projects and More...\">\n                <i class=\"fal fa-search\"></i>\n            </button>\n        </div>\n    </form>\n    {{#if theme_settings.logo-position '==' 'center'}}\n        <section class=\"quickSearchResults quick-search\" data-bind=\"html: results\"></section>\n    {{/if}}\n    </div>\n</div>\n","components/epicHeader/top-bar":"<div class=\"container\">\n    <div class=\"row top-bar-inner\">\n        <div class=\"col-lg-auto d-none d-lg-block\">\n            <ul class=\"top-contact-info\">\n                {{#if theme_settings.show_phone_header}}\n                <li>\n                    <a href=\"tel:{{settings.phone_number}}\">\n                        <span class=\"icon\">\n                            <svg><use xlink:href=\"#icon-telephone\" /></svg> \n                        </span>\n                        {{settings.phone_number}}\n                    </a>\n                </li>\n                {{/if}}\n                {{#if theme_settings.show_email_header}}\n                <li>\n                    <a href=\"mailto:{{theme_settings.epic_email_address}}\">\n                        <span class=\"icon\">\n                            <svg><use xlink:href=\"#icon-email\" /></svg> \n                        </span>\n                        {{theme_settings.epic_email_address}}\n                    </a>\n                </li>\n                {{/if}}\n            </ul>\n        </div>\n        <div class=\"col-auto ml-auto navUser text-right\">\n            <ul class=\"navUser-section top-bar-menu\">\n                {{#if theme_settings.logo-position '==' 'center'}}\n                    <li>\n                        <a class=\"navUser-action navUser-action--quickSearch\" href=\"#\" data-search=\"quickSearch\" aria-controls=\"quickSearch\" aria-expanded=\"false\">\n                            <i class=\"fal fa-search\"></i>\n                        </a>\n                    </li>\n                {{/if}}\n                <li>\n                    <a class=\"navUser-item--compare\" href=\"{{urls.compare}}\" data-compare-nav>{{lang 'common.compare'}} <span class=\"countPill countPill--positive\"></span></a>\n                </li>\n                {{#if theme_settings.left-category-menu '==' ''}}\n                    <li class=\"menu-item-dropdown\">\n                        <a href=\"javascript:void(0)\"><i class=\"fal fa-user\"></i>{{#if customer}} <span>Hi,</span> {{customer.name}}{{else}} {{lang 'common.account'}}{{/if}}</a>\n                        <ul class=\"menu-dropdown-list account-dropdown\">\n                            {{#if customer}}\n                            <li>\n                                <a href=\"{{urls.account.orders.all}}\">{{lang 'account.nav.orders'}}</a>\n                            </li>\n                            {{#if settings.returns_enabled}}\n                                <li>\n                                    <a href=\"{{urls.account.returns}}\">{{lang 'account.nav.returns'}}</a>\n                                </li>\n                            {{/if}}\n                            <li>\n                                <a href=\"{{urls.account.inbox}}\">{{lang 'account.mobile_nav.messages'}}</a>\n                            </li>\n                            <li>\n                                <a href=\"{{urls.account.addresses}}\">{{lang 'account.nav.addresses'}}</a>\n                            </li>\n                            {{#if settings.show_payment_methods}}\n                                <li>\n                                    <a href=\"{{urls.account.payment_methods.all}}\">{{lang 'account.nav.payment_methods'}}</a>\n                                </li>\n                            {{/if}}\n                            <li>\n                                <a href=\"{{urls.account.wishlists.all}}\">{{lang 'account.mobile_nav.wishlists'}}</a>\n                            </li>\n                            <li>\n                                <a href=\"{{urls.account.recent_items}}\">{{lang 'account.nav.recently_viewed'}}</a>\n                            </li>\n                            <li>\n                                <a href=\"{{urls.account.details}}\">{{lang 'account.nav.settings'}}</a>\n                            </li>\n                            <li>\n                                <a href=\"{{urls.auth.logout}}\">{{lang 'common.logout'}}</a>\n                            </li>\n                            {{else}}\n                                <li>\n                                    <a href=\"{{urls.auth.login}}\">{{lang 'common.login'}}</a>\n                                </li>\n                                {{#if settings.account_creation_enabled}}\n                                    <li class=\"signup\">\n                                        <a href=\"{{urls.auth.create_account}}\">{{lang 'common.sign_up'}}</a>\n                                    </li>\n                                {{/if}}\n                            {{/if}}\n                        </ul>\n                    </li>\n                {{/if}}\n                {{#if settings.gift_certificates_enabled}}\n                    <li>\n                        <a href=\"{{urls.gift_certificate.purchase}}\"><i class=\"fal fa-gift\"></i> {{lang 'common.gift_cert'}}</a>\n                    </li>\n                {{/if}}\n            </ul>\n            \n            <div class=\"top-currency-selector\">\n                {{> components/common/currency-selector}}\n            </div>\n        </div>\n    </div>\n</div><!--container-->\n{{#if theme_settings.logo-position '==' 'center'}}\n    <div class=\"dropdown dropdown--quickSearch\" id=\"quickSearch\" aria-hidden=\"true\" tabindex=\"-1\" data-prevent-quick-search-close>\n        {{> components/epicHeader/search}}\n    </div>\n{{/if}}\n","components/epicNavbar/default-nav-item":"\n{{#if children}}\n<a class=\"navPages-action has-subMenu\" href=\"{{url}}\">{{name}} <i class=\"icon navPages-action-moreIcon\" aria-hidden=\"true\"><svg><use xlink:href=\"#icon-chevron-down\" /></svg></i>\n</a>\n<div class=\"navPage-subMenu\" id=\"navPages-{{id}}\" aria-hidden=\"true\" tabindex=\"-1\">\n    <div class=\"container\">\n        <div class=\"row\">\n            <div class=\"col-12 submenu-column{{#if theme_settings.nav-category-one-name '=='name}}{{#if theme_settings.nav-category-right-image-one}} col-lg-8{{/if}}{{/if}}{{#if theme_settings.nav-category-two-name '=='name}}{{#if theme_settings.nav-category-right-image-two}} col-lg-8{{/if}}{{/if}}{{#if theme_settings.nav-category-three-name '=='name}}{{#if theme_settings.nav-category-right-image-three}} col-lg-8{{/if}}{{/if}}{{#if theme_settings.nav-category-four-name '=='name}}{{#if theme_settings.nav-category-right-image-four}} col-lg-8{{/if}}{{/if}}{{#if theme_settings.nav-category-five-name '=='name}}{{#if theme_settings.nav-category-right-image-five}} col-lg-8{{/if}}{{/if}}\">\n                <ul class=\"navPage-subMenu-list\">\n                    <!-- <li class=\"navPage-subMenu-item subMenu-viewAll\">\n                        <a class=\"navPage-subMenu-action navPages-action\" href=\"{{url}}\">{{lang 'category.view_all.name' category=name}}</a>\n                    </li> -->\n                    {{#each children}}\n                        <li class=\"navPage-subMenu-item\">\n                            {{#if children}}\n                                <a\n                                    class=\"navPage-subMenu-action navPages-action has-subMenu\"\n                                    href=\"{{url}}\">\n                                    {{name}}<i class=\"icon navPages-action-moreIcon\" aria-hidden=\"true\"><svg><use xlink:href=\"#icon-chevron-down\" /></svg></i>\n                                </a>\n                                <ul class=\"navPage-childList\" id=\"navPages-{{id}}\">\n                                    {{#each children}}\n                                    <li class=\"navPage-childList-item\">\n                                        {{#if children}}\n                                            <a class=\"navPage-childList-action navPages-action\" href=\"{{url}}\">{{name}}</a>\n                                            <ul class=\"navPage-childList\" id=\"navPages-{{id}}\">\n                                                {{#each children}}\n                                                <li class=\"navPage-childList-item\">\n                                                    <a class=\"navPage-childList-action navPages-action\" href=\"{{url}}\">{{name}}</a>\n                                                </li>\n                                                {{/each}}\n                                            </ul>\n                                        {{else}}\n                                            <a class=\"navPage-childList-action navPages-action\" href=\"{{url}}\">{{name}}</a>\n                                        {{/if}}\n                                    </li>\n                                    {{/each}}\n                                </ul>\n                            {{else}}\n                                <a class=\"as navPage-subMenu-action navPages-action\" href=\"{{url}}\">{{name}}</a>\n                            {{/if}}\n                        </li>\n                    {{/each}}\n                </ul>\n            </div>\n            {{#if theme_settings.nav-category-one-name '=='name}}\n                {{#if theme_settings.nav-category-right-image-one}}\n                    <div class=\"col-12 col-lg-4 submenu-img-column\">\n                        <a href=\"{{theme_settings.nav-category-right-url-one}}\">\n                            <img src=\"{{getImage theme_settings.nav-category-right-image-one}}\">\n                        </a>\n                    </div>\n                {{/if}}\n                {{#if theme_settings.nav-category-bottom-image-one}}\n                    <div class=\"col-12 col-lg-12 submenu-img-bottom\">\n                        <a href=\"{{theme_settings.nav-category-bottom-url-one}}\">\n                            <img src=\"{{getImage theme_settings.nav-category-bottom-image-one}}\">\n                        </a>\n                    </div>\n                {{/if}}\n            {{/if}}\n            {{#if theme_settings.nav-category-two-name '=='name}}\n                {{#if theme_settings.nav-category-right-image-two}}\n                    <div class=\"col-12 col-lg-4 submenu-img-column\">\n                        <a href=\"{{theme_settings.nav-category-right-url-two}}\">\n                            <img src=\"{{getImage theme_settings.nav-category-right-image-two}}\">\n                        </a>\n                    </div>\n                {{/if}}\n                {{#if theme_settings.nav-category-bottom-image-two}}\n                    <div class=\"col-12 col-lg-12 submenu-img-bottom\">\n                        <a href=\"{{theme_settings.nav-category-bottom-url-two}}\">\n                            <img src=\"{{getImage theme_settings.nav-category-bottom-image-two}}\">\n                        </a>\n                    </div>\n                {{/if}}\n            {{/if}}\n            {{#if theme_settings.nav-category-three-name '=='name}}\n                {{#if theme_settings.nav-category-right-image-three}}\n                    <div class=\"col-12 col-lg-4 submenu-img-column\">\n                        <a href=\"{{theme_settings.nav-category-right-url-three}}\">\n                            <img src=\"{{getImage theme_settings.nav-category-right-image-three}}\">\n                        </a>\n                    </div>\n                {{/if}}\n                {{#if theme_settings.nav-category-bottom-image-three}}\n                    <div class=\"col-12 col-lg-12 submenu-img-bottom\">\n                        <a href=\"{{theme_settings.nav-category-bottom-url-three}}\">\n                            <img src=\"{{getImage theme_settings.nav-category-bottom-image-three}}\">\n                        </a>\n                    </div>\n                {{/if}}\n            {{/if}}\n            {{#if theme_settings.nav-category-four-name '=='name}}\n                {{#if theme_settings.nav-category-right-image-four}}\n                    <div class=\"col-12 col-lg-4 submenu-img-column\">\n                        <a href=\"{{theme_settings.nav-category-right-url-four}}\">\n                            <img src=\"{{getImage theme_settings.nav-category-right-image-four}}\">\n                        </a>\n                    </div>\n                {{/if}}\n                {{#if theme_settings.nav-category-bottom-image-four}}\n                    <div class=\"col-12 col-lg-12 submenu-img-bottom\">\n                        <a href=\"{{theme_settings.nav-category-bottom-url-four}}\">\n                            <img src=\"{{getImage theme_settings.nav-category-bottom-image-four}}\">\n                        </a>\n                    </div>\n                {{/if}}\n            {{/if}}\n            {{#if theme_settings.nav-category-five-name '=='name}}\n                {{#if theme_settings.nav-category-right-image-five}}\n                    <div class=\"col-12 col-lg-4 submenu-img-column\">\n                        <a href=\"{{theme_settings.nav-category-right-url-five}}\">\n                            <img src=\"{{getImage theme_settings.nav-category-right-image-five}}\">\n                        </a>\n                    </div>\n                {{/if}}\n                {{#if theme_settings.nav-category-bottom-image-five}}\n                    <div class=\"col-12 col-lg-12 submenu-img-bottom\">\n                        <a href=\"{{theme_settings.nav-category-bottom-url-five}}\">\n                            <img src=\"{{getImage theme_settings.nav-category-bottom-image-five}}\">\n                        </a>\n                    </div>\n                {{/if}}\n            {{/if}}\n        </div>\n    </div>\n</div>\n{{else}}\n<a class=\"navPages-action\" href=\"{{url}}\">{{name}}</a>\n{{/if}}\n","components/epicNavbar/default-nav-menu":"<div class=\"container\">\n    {{#if theme_settings.mega-menu}}\n    <div class=\"row\">\n        <div class=\"col-lg-12 navPages-container\">\n            <nav class=\"navPages {{theme_settings.column-per-row}}\">\n                <ul class=\"navPages-list\">\n                    <li class=\"navPages-item navPages-item-page\">\n                        <a class=\"navPages-action{{#if name '==' ../page.title}} activePage{{/if}}\"\n                           href=\"/\"\n                           aria-label=\"Home\"\n                        >\n                            Home\n                        </a>\n                    </li>\n                    {{#each categories}}\n                        <li class=\"navPages-item\">\n                            {{> components/epicNavbar/default-nav-item theme_settings=../theme_settings}}\n                        </li>\n                    {{/each}}\n                    {{#unless theme_settings.hide_content_navigation}}\n                        {{#each pages}}\n                             <li class=\"navPages-item navPages-item-page\">\n                                {{#if children}}\n                                <a class=\"navPages-action has-subMenu\" href=\"{{url}}\">{{name}} <i class=\"icon navPages-action-moreIcon\" aria-hidden=\"true\"><svg><use xlink:href=\"#icon-chevron-down\" /></svg></i></a>\n                                <div class=\"navPage-subMenu\" id=\"navPages-index{{@index}}\" aria-hidden=\"true\" tabindex=\"-1\">\n                                    <ul class=\"navPage-subMenu-list\">\n                                        {{#each children}}\n                                        <li class=\"navPage-subMenu-item\">\n                                            <a class=\"navPage-subMenu-action navPages-action\" href=\"{{url}}\">{{name}}</a>\n                                        </li>\n                                        {{/each}}\n                                    </ul>\n                                </div>\n                                {{else}}\n                                    <a class=\"navPages-action\" href=\"{{url}}\">{{name}}</a>\n                                {{/if}}\n                             </li>\n                         {{/each}}\n                     {{/unless}}\n                </ul>\n            </nav>\n        </div>\n    </div>\n    {{else}}\n    <nav class=\"navPages nav-without-mm\">\n            <ul class=\"navPages-list\">\n                {{#each categories}}\n                    <li class=\"navPages-item\">\n                        {{> components/common/navigation-list-alternate}}\n                    </li>\n                {{/each}}\n                {{#unless theme_settings.hide_content_navigation}}\n                    {{#each pages}}\n                         <li class=\"navPages-item navPages-item-page\">\n                            {{#if children}}\n                            <a class=\"navPages-action has-subMenu\" href=\"{{url}}\">{{name}} <i class=\"icon navPages-action-moreIcon\" aria-hidden=\"true\"><svg><use xlink:href=\"#icon-chevron-down\" /></svg></i></a>\n                            <div class=\"navPage-subMenu\" id=\"navPages-index{{@index}}\" aria-hidden=\"true\" tabindex=\"-1\">\n                                <ul class=\"navPage-subMenu-list\">\n                                    {{#each children}}\n                                    <li class=\"navPage-subMenu-item\">\n                                        <a class=\"navPage-subMenu-action navPages-action\" href=\"{{url}}\">{{name}}</a>\n                                    </li>\n                                    {{/each}}\n                                </ul>\n                            </div>\n                            {{else}}\n                                <a class=\"navPages-action\" href=\"{{url}}\">{{name}}</a>\n                            {{/if}}\n                         </li>\n                     {{/each}}\n                 {{/unless}}\n            </ul>\n        </nav>\n    {{/if}}\n</div>\n","components/epicNavbar/sidebar-category-menu":"<div class=\"container sc-menu-container\">\n\t<div class=\"row align-items-center\">\n\t\t<div class=\"col-md-3 nc-button-col p-0\">\n\t\t\t\t<a class=\"nc-button\" href=\"javascript:void(0);\"><i class=\"fal fa-bars\"></i>\n Shop by Category</a>\n\t\t\t<div class=\"sc-navmenu\">\n                {{#if theme_settings.mega-menu}}\n    \t\t\t\t<nav class=\"navPages nav-with-mm {{theme_settings.column-per-row}}\">\n    \t\t\t\t\t<ul class=\"navPages-list\">\n    \t\t\t\t        {{#each categories}}\n    \t\t\t\t            <li class=\"navPages-item\">\n                                    {{> components/epicNavbar/default-nav-item theme_settings=../theme_settings}}\n    \t\t\t                </li>\n    \t\t\t\t        {{/each}}\n    \t\t\t\t    </ul>\n    \t\t\t\t</nav>\n                {{else}}\n                    <nav class=\"navPages nav-without-mm\">\n                        <ul class=\"navPages-list\">\n                            {{#each categories}}\n                                <li class=\"navPages-item\">\n                                    {{> components/common/navigation-list-alternate}}\n                                </li>\n                            {{/each}}\n                        </ul>\n                    </nav>\n                {{/if}}\n\t\t\t</div>\n\t\t</div>\n        {{#unless theme_settings.hide_content_navigation}}\n    \t\t<div class=\"col-md\">\n                <nav class=\"hws-pages-menu navPages\">\n                    <ul>\n                        {{#each pages}}\n                            <li class=\"navPages-item navPages-item-page\">\n                                {{#if children}}\n                                <a class=\"navPages-action has-subMenu\" href=\"{{url}}\" data-collapsible=\"navPages-index{{@index}}\">{{name}} <i class=\"icon navPages-action-moreIcon\" aria-hidden=\"true\"><svg><use xlink:href=\"#icon-chevron-down\" /></svg></i></a>\n                                <div class=\"navPage-subMenu\" id=\"navPages-index{{@index}}\" aria-hidden=\"true\" tabindex=\"-1\">\n                                    <ul class=\"navPage-subMenu-list\">\n                                        {{#each children}}\n                                        <li class=\"navPage-subMenu-item\">\n                                            <a class=\"navPage-subMenu-action navPages-action\" href=\"{{url}}\">{{name}}</a>\n                                        </li>\n                                        {{/each}}\n                                    </ul>\n                                </div>\n                                {{else}}\n                                    <a class=\"navPages-action\" href=\"{{url}}\">{{name}}</a>\n                                {{/if}}\n                            </li>\n                        {{/each}}\n                    </ul>\n                </nav>\n    \t\t</div>\n        {{/unless}}\n        <div class=\"col-md-auto ml-auto\">\n            <div class=\"nav-user-item\">\n                <a class=\"nu-button\" href=\"javascript:void(0)\">{{#if customer}}<span>Hi,</span> {{customer.name}}{{else}}<span>{{lang 'common.login'}}</span> {{lang 'common.account'}}{{/if}} <i class=\"fal fa-angle-down\"></i></a>\n                <ul class=\"nu-item-dropdown\">\n                    {{#if customer}}\n                    <li>\n                        <a href=\"{{urls.account.orders.all}}\">{{lang 'account.nav.orders'}}</a>\n                    </li>\n                    {{#if settings.returns_enabled}}\n                        <li>\n                            <a href=\"{{urls.account.returns}}\">{{lang 'account.nav.returns'}}</a>\n                        </li>\n                    {{/if}}\n                    <li>\n                        <a href=\"{{urls.account.inbox}}\">{{lang 'account.mobile_nav.messages'}}</a>\n                    </li>\n                    <li>\n                        <a href=\"{{urls.account.addresses}}\">{{lang 'account.nav.addresses'}}</a>\n                    </li>\n                    {{#if settings.show_payment_methods}}\n                        <li>\n                            <a href=\"{{urls.account.payment_methods.all}}\">{{lang 'account.nav.payment_methods'}}</a>\n                        </li>\n                    {{/if}}\n                    <li>\n                        <a href=\"{{urls.account.wishlists.all}}\">{{lang 'account.mobile_nav.wishlists'}}</a>\n                    </li>\n                    <li>\n                        <a href=\"{{urls.account.recent_items}}\">{{lang 'account.nav.recently_viewed'}}</a>\n                    </li>\n                    <li>\n                        <a href=\"{{urls.account.details}}\">{{lang 'account.nav.settings'}}</a>\n                    </li>\n                    <li>\n                        <a href=\"{{urls.auth.logout}}\">{{lang 'common.logout'}}</a>\n                    </li>\n                    {{else}}\n                        <li>\n                            <a href=\"{{urls.auth.login}}\">{{lang 'common.login'}}</a>\n                        </li>\n                        {{#if settings.account_creation_enabled}}\n                            <li class=\"signup\">\n                                <a href=\"{{urls.auth.create_account}}\">{{lang 'common.sign_up'}}</a>\n                            </li>\n                        {{/if}}\n                    {{/if}}\n                </ul>\n            </div>\n        </div>\n        {{#or customer (if theme_settings.restrict_to_login '!==' true)}}\n            <div class=\"col col-auto\">\n                <div class=\"cart-section\">\n                    <div class=\"cart-items\">\n                        <span class=\"cart-quantity cart-items-count\">{{cart.quantity}}</span>\n                        <span class=\"icon\">\n                            <svg><use xlink:href=\"#icon-shopping-cart\" /></svg> \n                        </span>\n                    </div>\n                    <div class=\"cart-subtotal\">\n                        <a\n                            class=\"view-cart\"\n                            data-cart-preview\n                            data-dropdown=\"cart-preview-dropdown\"\n                            href=\"{{urls.cart}}\" aria-label=\"{{lang 'cart.nav_aria_label'}}\">\n                           <span>My Cart</span><br><span class=\"ct-price\">{{cart.grand_total.formatted}}</span> <i class=\"icon\" aria-hidden=\"true\"><svg><use xlink:href=\"#icon-chevron-down\" /></svg></i>\n                        </a>\n                        <div class=\"dropdown-menu\" id=\"cart-preview-dropdown\" data-dropdown-content aria-hidden=\"true\"></div>\n                    </div>\n                </div>\n            </div>\n            {{else}}\n        {{/or}}\n        \n\t</div>\n</div>\n"}
